{
  "name": "Alvin Henry",
  "age": 41,
  "address": {
    "street": "Nugnub Glen",
    "city": "Bugomobon",
    "state": "NC",
    "zip": "28651"
  },
  "contact": {
    "phone": "(469) 202-4505",
    "servicePhone": "800828281"
  },
  "birthday": "1972-06-28T07:54:19.377Z",
  "ip": "34.129.62.5",
  "foo": "bar",
  "profile": {
    "about": "Reh igjejjeb nare duve ifawoada bovweb ze dochitho vazuna meab osase igadukoh dokic voho nibwi pife jejnuba. Fopa bof ruceb eb donzol ho wibsi tu baceca esa momu nu ta. Piwfabput jewembu mieruki decdumot viidunas duav cizcamec venad et tag uj agtedum irefri rem vilcosko haldiwhov mokus zen. Jiw foruh can mufejpa kos ol owko sa lu iv hecbalsem juaz ka.",
    "bio": "Jap muculec nomi ci hasdauge hud ce pigecte juvecwe kabi mugupuc okeluvvob ce. Wubotbeg tuddevsot le sij fo gap waki taruvfug erkup afujir mabe fap ogulallo bilujeh piscoraw vujri. Digro hepkiub tow ruf bojwojof hek bohawdu jazmemlo tubhaji careferav lalu ime hacelcut dap. Hiinzun mehibi obrabtep nuzuhiho goz bivme mutpaca sebifu sidgokpuz ibu otaf hedik nohaz pakum zaswitge soculbo. Hupvarji gojafroz ve nuzse megzoja pi bessouh tene umzazrus kannun vim rifad. Duv tizuhok muwip odekuur wu wuku sooga beofe lis nosizgo erirora rauv ediso fanra zuf cavu wefcoglif. Zizviz lemoruh dop loasawur lejiv viigce cum luaga alna marut fufhi ozrabhuc unalu lunjuc riokogoc agdod wu wi."
  },
  "apiKey": "688f39d84d89d4593036b16018eb9427493c61b78687bf9b6bf428ace6ea3703",
  "currency": {
    "code": "GHS",
    "name": "Ghana Cedi"
  }
}